bitbazaar_rs-0.0.3.dist-info/METADATA
bitbazaar_rs-0.0.3.dist-info/WHEEL
bitbazaar_rs-0.0.3.dist-info/license_files/LICENSE.md
bitbazaar_rs-0.0.3.dist-info/license_files/LICENSE.zetch.md
bitbazaar_rs/py.typed
bitbazaar_rs/rust-toolchain.toml
bitbazaar_rs/utils.pyi
bitbazaar_rs/__init__.py
bitbazaar_rs/__init__.pyi
bitbazaar_rs/_rs.cp311-win32.pyd
bitbazaar_rs-0.0.3.dist-info/RECORD
