Metadata-Version: 2.1
Name: bitbazaar_rs
Version: 0.0.3
Classifier: Development Status :: 1 - Planning
Classifier: Typing :: Typed
Classifier: Operating System :: POSIX :: Linux
Classifier: Operating System :: Microsoft :: Windows
Classifier: Operating System :: MacOS
Classifier: Programming Language :: Python
Classifier: Programming Language :: Python :: Implementation :: CPython
Classifier: Programming Language :: Python :: 3
Classifier: Programming Language :: Python :: 3 :: Only
Classifier: Programming Language :: Python :: 3.11
Classifier: Programming Language :: Python :: 3.12
Classifier: Programming Language :: Rust
Classifier: License :: OSI Approved
License-File: LICENSE.md
License-File: LICENSE.zetch.md
Summary: An assortment of publicly available cross-language utilities useful to my projects.
Author-email: Zachary Stucke <zakstucke@gmail.com>
License: MIT
Requires-Python: >=3.11
Project-URL: Sourcecode, https://github.com/zakstucke/bitbazaar
Project-URL: Documentation, https://zakstucke.github.io/bitbazaar
